cheap_pie/__init__.py
cheap_pie/output.xml
cheap_pie/tdump.txt
cheap_pie/cheap_pie_core/__init__.py
cheap_pie/cheap_pie_core/cbitfield.py
cheap_pie/cheap_pie_core/cheap_pie_main.py
cheap_pie/cheap_pie_core/cp_banner.py
cheap_pie/cheap_pie_core/cp_builder.py
cheap_pie/cheap_pie_core/cp_cli.py
cheap_pie/cheap_pie_core/cp_hal.py
cheap_pie/cheap_pie_core/cp_register.py
cheap_pie/cheap_pie_core/test.py
cheap_pie/cmsis-svd-data-main/data/STMicro/fill_contents.py
cheap_pie/parsers/__init__.py
cheap_pie/parsers/cp_parsers_wrapper.py
cheap_pie/parsers/ipxact_parse.py
cheap_pie/parsers/ipyxact_parse.py
cheap_pie/parsers/rdl_parse.py
cheap_pie/parsers/svd_parse.py
cheap_pie/parsers/svd_parse_repo.py
cheap_pie/parsers/xml_xslt.py
cheap_pie/scripts/cp_hal2doc.py
cheap_pie/scripts/cp_interactive.py
cheap_pie/tools/__init__.py
cheap_pie/tools/hal2doc.py
cheap_pie/tools/rdl2any.py
cheap_pie/tools/search.py
cheap_pie/transport/__init__.py
cheap_pie/transport/cp_dummy_transport.py
cheap_pie/transport/cp_esptool_transport.py
cheap_pie/transport/cp_jlink_transport.py
cheap_pie/transport/cp_pyocd_transport.py
cheap_pie/transport/cp_pyverilator_transport.py
cheap_pie-1.2.5.dist-info/LICENSE
cheap_pie-1.2.5.dist-info/METADATA
cheap_pie-1.2.5.dist-info/WHEEL
cheap_pie-1.2.5.dist-info/entry_points.txt
cheap_pie-1.2.5.dist-info/top_level.txt
cheap_pie-1.2.5.dist-info/RECORD
