Metadata-Version: 2.1
Name: cheap_pie
Version: 1.2.5
Summary: A python tool for silicon validation.
Author-email: Marco Merlin <marcomerli@gmail.com>
Project-URL: Homepage, https://github.com/bat52/cheap_pie
Project-URL: Source, https://github.com/bat52/cheap_pie
Project-URL: Tracker, https://github.com/bat52/cheap_pie/issues
Keywords: python,silicon,validation
Classifier: Programming Language :: Python :: 3
Classifier: Operating System :: OS Independent
Requires-Python: >=3.8
License-File: LICENSE
Requires-Dist: untangle
Requires-Dist: hickle
Requires-Dist: cmsis-svd
Requires-Dist: ipyxact
Requires-Dist: python-docx
Requires-Dist: wavedrom
Requires-Dist: wavedrom-ascii
Requires-Dist: pyverilator-mm
Requires-Dist: peakrdl-ipxact
Requires-Dist: peakrdl-uvm
Requires-Dist: peakrdl-verilog
Requires-Dist: peakrdl-cheader
Requires-Dist: requests
